dbl/__init__.py
dbl/client.py
dbl/errors.py
dbl/http.py
dblpy-0.4.0.dist-info/LICENSE
dblpy-0.4.0.dist-info/METADATA
dblpy-0.4.0.dist-info/WHEEL
dblpy-0.4.0.dist-info/top_level.txt
dblpy-0.4.0.dist-info/RECORD
