Metadata-Version: 1.2
Name: dblpy
Version: 0.4.0
Summary: A simple API wrapper for top.gg written in Python.
Home-page: https://github.com/top-gg/DBL-Python-Library
Author: Assanali Mukhanov, top.gg
Author-email: shivaco.osu@gmail.com
License: MIT
Keywords: discord bot list discordbots botlist topgg top.gg
Platform: UNKNOWN
Classifier: Development Status :: 5 - Production/Stable
Classifier: License :: OSI Approved :: MIT License
Classifier: Intended Audience :: Developers
Classifier: Natural Language :: English
Classifier: Operating System :: OS Independent
Classifier: Programming Language :: Python :: 3 :: Only
Classifier: Programming Language :: Python :: 3.5
Classifier: Programming Language :: Python :: 3.6
Classifier: Programming Language :: Python :: 3.7
Classifier: Programming Language :: Python :: 3.8
Classifier: Topic :: Internet
Classifier: Topic :: Software Development :: Libraries
Classifier: Topic :: Software Development :: Libraries :: Python Modules
Classifier: Topic :: Utilities
Requires-Python: >= 3.5.3
